{
  "openapi": "3.0.1",
  "info": {
    "title": "AuthPortal.Api",
    "version": "1.0"
  },
  "paths": {
    "/api/User": {
      "get": {
        "tags": [
          "User"
        ],
        "parameters": [
          {
            "name": "Id",
            "in": "query",
            "schema": {
              "type": "string",
              "format": "uuid"
            }
          }
        ],
        "responses": {
          "200": {
            "description": "OK",
            "content": {
              "text/plain": {
                "schema": {
                  "$ref": "#/components/schemas/GetUserResponse"
                }
              },
              "application/json": {
                "schema": {
                  "$ref": "#/components/schemas/GetUserResponse"
                }
              },
              "text/json": {
                "schema": {
                  "$ref": "#/components/schemas/GetUserResponse"
                }
              }
            }
          }
        }
      }
    }
  },
  "components": {
    "schemas": {
      "Gender": {
        "enum": [
          1,
          2
        ],
        "type": "integer",
        "format": "int32"
      },
      "GetUserResponse": {
        "type": "object",
        "properties": {
          "statusCode": {
            "type": "integer",
            "format": "int32",
            "nullable": true
          },
          "success": {
            "type": "boolean",
            "nullable": true
          },
          "message": {
            "type": "string",
            "nullable": true
          },
          "id": {
            "type": "string",
            "format": "uuid"
          },
          "firstName": {
            "type": "string",
            "nullable": true
          },
          "lastName": {
            "type": "string",
            "nullable": true
          },
          "type": {
            "$ref": "#/components/schemas/UserType"
          },
          "dateOfBirth": {
            "type": "string",
            "format": "date-time",
            "nullable": true
          },
          "balance": {
            "type": "number",
            "format": "double"
          },
          "identityNumber": {
            "type": "string",
            "nullable": true
          },
          "email": {
            "type": "string",
            "nullable": true
          },
          "emailConfirmed": {
            "type": "string",
            "nullable": true
          },
          "gender": {
            "$ref": "#/components/schemas/Gender"
          },
          "registerDate": {
            "type": "string",
            "format": "date-time"
          }
        },
        "additionalProperties": false
      },
      "UserType": {
        "enum": [
          0,
          1
        ],
        "type": "integer",
        "format": "int32"
      }
    }
  }
}